music_metadata_territories-24.12-py3.12-nspkg.pth
music_metadata/territories/__init__.py
music_metadata/territories/list.csv
music_metadata/territories/territory.py
music_metadata/territories/territory_list.py
music_metadata/territories/tests.py
music_metadata/territories/tree.csv
music_metadata_territories-24.12.dist-info/LICENSE
music_metadata_territories-24.12.dist-info/METADATA
music_metadata_territories-24.12.dist-info/WHEEL
music_metadata_territories-24.12.dist-info/namespace_packages.txt
music_metadata_territories-24.12.dist-info/top_level.txt
music_metadata_territories-24.12.dist-info/RECORD
