Metadata-Version: 2.1
Name: music_metadata_territories
Version: 24.12
Summary: Music Metedata - Territory-related tools
Home-page: https://matijakolaric.com/development/musicmetadata/
Author: Matija Kolarić
Author-email: matijakolaric@users.noreply.github.com
Project-URL: Created by, https://matijakolaric.com
Project-URL: Code Repository, https://github.com/musicmetadata/territories
Classifier: Development Status :: 5 - Production/Stable
Classifier: Environment :: Web Environment
Classifier: Intended Audience :: Developers
Classifier: License :: OSI Approved :: MIT License
Classifier: Operating System :: OS Independent
Classifier: Programming Language :: Python :: 3
Classifier: Programming Language :: Python :: 3 :: Only
Classifier: Programming Language :: Python :: 3.11
Classifier: Programming Language :: Python :: 3.12
Requires-Python: >=3.11
License-File: LICENSE
